bioutensil/__init__.py
bioutensil/bam.py
bioutensil/bash.py
bioutensil/basic.py
bioutensil/clustering.py
bioutensil/cnv.py
bioutensil/complex_haplotype.py
bioutensil/constants.py
bioutensil/converter.py
bioutensil/csv_aux.py
bioutensil/fasta.py
bioutensil/gene.py
bioutensil/genome.py
bioutensil/genomic_region.py
bioutensil/module.py
bioutensil/myio.py
bioutensil/myprint.py
bioutensil/psl_tran.py
bioutensil/sequence.py
bioutensil/shell.py
bioutensil/structure_variant.py
bioutensil/vcf_aux.py
bioutensil/version.py
bioutensil/bio_database/hg19.chrom.size
bioutensil/bio_database/hg19.cytoBand.txt
bioutensil/bio_database/hg38.chrom.size
bioutensil/bio_database/hg38.cytoBand.txt
bioutensil/bio_database/barcodes/4M-with-alts-february-2016.txt
bioutensil/bio_database/ens75.hg19.gene/ens75.hg19.gene.f10.sorted.bed
bioutensil/bio_database/ens75.hg19.gene/ens75.hg19.gene.f10.sorted.bed.bgz
bioutensil/bio_database/oncogene/cell.cancer.dependency.map.79.gene.list
bioutensil/bio_database/ucsc.hg19.refSeq.refGene/ucsc.hg19.refSeq.refGene
bioutensil/bplot/__init__.py
bioutensil/bplot/axis.py
bioutensil/bplot/chromosome.py
bioutensil/bplot/colorbar.py
bioutensil/bplot/latex2svg.py
bioutensil/bplot/shape.py
bioutensil/bplot/svgbase.py
bioutensil/bplot/svgfigure.py
bioutensil/bplot/svgobject.py
bioutensil/bplot/table.py
bioutensil/bplot/text.py
bioutensil/mymath/__init__.py
bioutensil/mymath/mymath.py
bioutensil/mymath/significant_test.py
bioutensil-0.0.8.3.dist-info/LICENSE.txt
bioutensil-0.0.8.3.dist-info/METADATA
bioutensil-0.0.8.3.dist-info/WHEEL
bioutensil-0.0.8.3.dist-info/top_level.txt
bioutensil-0.0.8.3.dist-info/RECORD
